[{"metadata": {"mapping-verision": 1, "attack-version": 10, "creation-date": "03/28/2022", "last-update": "03/28/2022", "author": "", "contact": "ctid@mitre-engenuity.org", "organization": "", "platform": "GCP", "platform-version": "", "mapping-type": "scoring"}, "attack-object": {"id": "T1040", "name": "Network Sniffing", "value": "Certificate Authority Service", "mapping-pattern": "", "secondary-property": "", "comments": "", "references": ["https://cloud.google.com/certificate-authority-service/docs"], "score-category": "Protect", "score-value": "Minimal", "score-comment": "This control may mitigate against Network Sniffing by providing certificates for internal endpoints and applications to use with asymmetric encryption. This control helps protect the issuing Certificate Authority with the use of Google's IAM and policy controls.", "related-score": false, "tags": ["Certificate Service", "Network"]}}]