[{"metadata": {"mapping-version": 1, "attack-version": 9, "technology-domain": "enterprise", "author": "", "contact": "ctid@mitre-engenuity.org", "creation-date": "06/28/2021", "last-update": "", "organization": "", "mapping-platform": "AWS", "mapping-platform-version": ""}, "attack-object": {"comments": "", "id": "T1555", "name": "Credentials from Password Stores", "references": ["https://docs.aws.amazon.com/secretsmanager/latest/userguide/intro.html", "https://docs.aws.amazon.com/secretsmanager/latest/userguide/best-practices.html"], "tags": ["Credentials"], "mapping-description": "", "mapping-target": "AWS Secrets Manager", "mapping-platform": {"score-category": "Protect", "score-value": "Partial", "related-score": false, "tags": ["Credentials"]}}}, {"metadata": {"mapping-version": 1, "attack-version": 9, "technology-domain": "enterprise", "author": "", "contact": "ctid@mitre-engenuity.org", "creation-date": "06/28/2021", "last-update": "", "organization": "", "mapping-platform": "AWS", "mapping-platform-version": ""}, "attack-object": {"comments": "", "id": "T1212", "name": "Exploitation for Credential Access", "references": ["https://docs.aws.amazon.com/secretsmanager/latest/userguide/intro.html", "https://docs.aws.amazon.com/secretsmanager/latest/userguide/best-practices.html"], "tags": ["Credentials"], "mapping-description": "", "mapping-target": "AWS Secrets Manager", "mapping-platform": {"score-category": "Protect", "score-value": "Partial", "related-score": false, "tags": ["Credentials"]}}}, {"metadata": {"mapping-version": 1, "attack-version": 9, "technology-domain": "enterprise", "author": "", "contact": "ctid@mitre-engenuity.org", "creation-date": "06/28/2021", "last-update": "", "organization": "", "mapping-platform": "AWS", "mapping-platform-version": ""}, "attack-object": {"comments": "", "id": "T1528", "name": "Steal Application Access Token", "references": ["https://docs.aws.amazon.com/secretsmanager/latest/userguide/intro.html", "https://docs.aws.amazon.com/secretsmanager/latest/userguide/best-practices.html"], "tags": ["Credentials"], "mapping-description": "", "mapping-target": "AWS Secrets Manager", "mapping-platform": {"score-category": "Protect", "score-value": "Partial", "related-score": false, "tags": ["Credentials"]}}}, {"metadata": {"mapping-version": 1, "attack-version": 9, "technology-domain": "enterprise", "author": "", "contact": "ctid@mitre-engenuity.org", "creation-date": "06/28/2021", "last-update": "", "organization": "", "mapping-platform": "AWS", "mapping-platform-version": ""}, "attack-object": {"comments": "", "id": "T1552", "name": "Unsecured Credentials", "references": ["https://docs.aws.amazon.com/secretsmanager/latest/userguide/intro.html", "https://docs.aws.amazon.com/secretsmanager/latest/userguide/best-practices.html"], "tags": ["Credentials"], "mapping-description": "", "mapping-target": "AWS Secrets Manager", "mapping-platform": {"score-category": "Protect", "score-value": "Partial", "related-score": true, "tags": ["Credentials"]}}}]