[{"metadata": {"mapping-version": 1, "attack-version": 9, "technology-domain": "enterprise", "author": "", "contact": "ctid@mitre-engenuity.org", "creation-date": "06/07/2021", "last-update": "", "organization": "", "mapping-platform": "AWS", "mapping-platform-version": ""}, "attack-object": {"comments": "", "id": "T1078", "name": "Valid Accounts", "references": ["https://docs.aws.amazon.com/iam/index.html"], "tags": ["Identity", "Credentials"], "mapping-description": "", "mapping-target": "AWS Identity and Access Management", "mapping-platform": {"score-category": "Protect", "score-value": "Partial", "related-score": true, "tags": ["Identity", "Credentials"]}}}, {"metadata": {"mapping-version": 1, "attack-version": 9, "technology-domain": "enterprise", "author": "", "contact": "ctid@mitre-engenuity.org", "creation-date": "06/07/2021", "last-update": "", "organization": "", "mapping-platform": "AWS", "mapping-platform-version": ""}, "attack-object": {"comments": "", "id": "T1078", "name": "Valid Accounts", "references": ["https://docs.aws.amazon.com/iam/index.html"], "tags": ["Identity", "Credentials"], "mapping-description": "", "mapping-target": "AWS Identity and Access Management", "mapping-platform": {"score-category": "Detect", "score-value": "Partial", "related-score": true, "tags": ["Identity", "Credentials"]}}}, {"metadata": {"mapping-version": 1, "attack-version": 9, "technology-domain": "enterprise", "author": "", "contact": "ctid@mitre-engenuity.org", "creation-date": "06/07/2021", "last-update": "", "organization": "", "mapping-platform": "AWS", "mapping-platform-version": ""}, "attack-object": {"comments": "", "id": "T1098", "name": "Account Manipulation", "references": ["https://docs.aws.amazon.com/iam/index.html"], "tags": ["Identity", "Credentials"], "mapping-description": "", "mapping-target": "AWS Identity and Access Management", "mapping-platform": {"score-category": "Detect", "score-value": "Minimal", "related-score": true, "tags": ["Identity", "Credentials"]}}}, {"metadata": {"mapping-version": 1, "attack-version": 9, "technology-domain": "enterprise", "author": "", "contact": "ctid@mitre-engenuity.org", "creation-date": "06/07/2021", "last-update": "", "organization": "", "mapping-platform": "AWS", "mapping-platform-version": ""}, "attack-object": {"comments": "", "id": "T1550", "name": "Use Alternate Authentication Material", "references": ["https://docs.aws.amazon.com/iam/index.html"], "tags": ["Identity", "Credentials"], "mapping-description": "", "mapping-target": "AWS Identity and Access Management", "mapping-platform": {"score-category": "Protect", "score-value": "Minimal", "related-score": true, "tags": ["Identity", "Credentials"]}}}, {"metadata": {"mapping-version": 1, "attack-version": 9, "technology-domain": "enterprise", "author": "", "contact": "ctid@mitre-engenuity.org", "creation-date": "06/07/2021", "last-update": "", "organization": "", "mapping-platform": "AWS", "mapping-platform-version": ""}, "attack-object": {"comments": "", "id": "T1110", "name": "Brute Force", "references": ["https://docs.aws.amazon.com/iam/index.html"], "tags": ["Identity", "Credentials"], "mapping-description": "", "mapping-target": "AWS Identity and Access Management", "mapping-platform": {"score-category": "Protect", "score-value": "Significant", "related-score": true, "tags": ["Identity", "Credentials"]}}}, {"metadata": {"mapping-version": 1, "attack-version": 9, "technology-domain": "enterprise", "author": "", "contact": "ctid@mitre-engenuity.org", "creation-date": "06/07/2021", "last-update": "", "organization": "", "mapping-platform": "AWS", "mapping-platform-version": ""}, "attack-object": {"comments": "", "id": "T1528", "name": "Steal Application Access Token", "references": ["https://docs.aws.amazon.com/iam/index.html"], "tags": ["Identity", "Credentials"], "mapping-description": "", "mapping-target": "AWS Identity and Access Management", "mapping-platform": {"score-category": "Protect", "score-value": "Minimal", "related-score": false, "tags": ["Identity", "Credentials"]}}}]