[{"metadata": {"mapping-version": 1, "attack-version": 8.2, "technology-domain": "enterprise", "author": "", "contact": "ctid@mitre-engenuity.org", "creation-date": "03/01/2021", "last-update": "", "organization": "", "mapping-platform": "Azure", "mapping-platform-version": ""}, "attack-object": {"comments": "", "id": "T1580", "name": "Cloud Infrastructure Discovery", "references": ["https://docs.microsoft.com/en-us/azure/security-center/defender-for-key-vault-introduction", "https://docs.microsoft.com/en-us/azure/security-center/alerts-reference#alerts-azurekv"], "tags": ["Azure Defender", "Azure Security Center Recommendation", "Credentials"], "mapping-description": "", "mapping-target": "Azure Defender for Key Vault", "mapping-platform": {"score-category": "Detect", "score-value": "Minimal", "related-score": false, "tags": ["Azure Defender", "Azure Security Center Recommendation", "Credentials"]}}}, {"metadata": {"mapping-version": 1, "attack-version": 8.2, "technology-domain": "enterprise", "author": "", "contact": "ctid@mitre-engenuity.org", "creation-date": "03/01/2021", "last-update": "", "organization": "", "mapping-platform": "Azure", "mapping-platform-version": ""}, "attack-object": {"comments": "", "id": "T1555", "name": "Credentials from Password Stores", "references": ["https://docs.microsoft.com/en-us/azure/security-center/defender-for-key-vault-introduction", "https://docs.microsoft.com/en-us/azure/security-center/alerts-reference#alerts-azurekv"], "tags": ["Azure Defender", "Azure Security Center Recommendation", "Credentials"], "mapping-description": "", "mapping-target": "Azure Defender for Key Vault", "mapping-platform": {"score-category": "Detect", "score-value": "Partial", "related-score": false, "tags": ["Azure Defender", "Azure Security Center Recommendation", "Credentials"]}}}]